MagicSelection/__init__.py
MagicSelection/feature_selection.py
MagicSelection/data/example-data.csv
MagicSelection-0.0.17.dist-info/LICENSE
MagicSelection-0.0.17.dist-info/METADATA
MagicSelection-0.0.17.dist-info/WHEEL
MagicSelection-0.0.17.dist-info/top_level.txt
MagicSelection-0.0.17.dist-info/RECORD
