Metadata-Version: 2.1
Name: MagicSelection
Version: 0.0.17
Summary: feature selection method with support for combined features
Home-page: https://github.com/dwu12/feature_selection
Download-URL: https://github.com/dwu12/feature_selection
Author: Di Wu
Author-email: wudi1629@gmail.com
Maintainer: Di Wu
Maintainer-email: wudi1629@gmail.com
License: MIT
License-File: LICENSE
Requires-Dist: numpy ==1.23.0
Requires-Dist: pandas ==1.5.0
Requires-Dist: scikit-learn ==1.1.0
Requires-Dist: mlxtend ==0.21.0
Requires-Dist: seaborn ==0.13.0
Requires-Dist: dill ==0.3.7
Requires-Dist: ipykernel ==6.26.0
